{
	"animations": [
		{
			"offsets": [
				3,
				0
			],
			"loop": false,
			"fps": 24,
			"anim": "idle",
			"indices": [],
			"name": "Pico Idle Dance"
		},
		{
			"offsets": [
				20,
				32
			],
			"loop": false,
			"fps": 24,
			"anim": "singUP",
			"indices": [],
			"name": "pico Up note0"
		},
		{
			"offsets": [
				92,
				-80
			],
			"loop": false,
			"fps": 24,
			"anim": "singDOWN",
			"indices": [],
			"name": "Pico Down Note0"
		},
		{
			"offsets": [
				89,
				-38
			],
			"loop": false,
			"fps": 24,
			"anim": "singDOWNmiss",
			"indices": [],
			"name": "Pico Down Note MISS"
		},
		{
			"offsets": [
				28,
				65
			],
			"loop": false,
			"fps": 24,
			"anim": "singUPmiss",
			"indices": [],
			"name": "pico Up note miss"
		},
		{
			"loop": false,
			"offsets": [
				-47,
				-5
			],
			"anim": "singRIGHT",
			"fps": 24,
			"name": "Pico Note Right0",
			"indices": []
		},
		{
			"loop": false,
			"offsets": [
				90,
				-10
			],
			"anim": "singLEFT",
			"fps": 24,
			"name": "Pico NOTE LEFT0",
			"indices": []
		},
		{
			"loop": false,
			"offsets": [
				-42,
				43
			],
			"anim": "singRIGHTmiss",
			"fps": 24,
			"name": "Pico Note Right Miss",
			"indices": []
		},
		{
			"loop": false,
			"offsets": [
				85,
				20
			],
			"anim": "singLEFTmiss",
			"fps": 24,
			"name": "Pico NOTE LEFT miss",
			"indices": []
		}
	],
	"no_antialiasing": false,
	"image": "characters/picolobbest",
	"position": [
		0,
		300
	],
	"healthicon": "pico",
	"flip_x": true,
	"healthbar_colors": [
		183,
		216,
		85
	],
	"camera_position": [
		220,
		0
	],
	"sing_duration": 4,
	"scale": 1
}