<?xml version='1.0' encoding='utf-8'?>
<TextureAtlas imagePath="black.png">
	
	
	<SubTexture name="down0000" x="4" y="4" width="564" height="328" />
	<SubTexture name="down0001" x="573" y="4" width="564" height="328" />
	<SubTexture name="down0002" x="573" y="4" width="564" height="328" />
	<SubTexture name="down0003" x="1143" y="4" width="564" height="328" />
	<SubTexture name="down0004" x="1143" y="4" width="564" height="328" />
	<SubTexture name="down0005" x="1712" y="4" width="564" height="328" />
	<SubTexture name="down0006" x="1712" y="4" width="564" height="328" />
	<SubTexture name="down0007" x="2281" y="4" width="564" height="328" />
	<SubTexture name="down0008" x="2281" y="4" width="564" height="328" />
	<SubTexture name="down0009" x="2851" y="4" width="564" height="328" />
	<SubTexture name="idle0000" x="4" y="336" width="513" height="292" />
	<SubTexture name="idle0001" x="4" y="336" width="513" height="292" />
	<SubTexture name="idle0002" x="522" y="336" width="513" height="292" />
	<SubTexture name="idle0003" x="1040" y="336" width="513" height="292" />
	<SubTexture name="idle0004" x="1559" y="336" width="513" height="292" />
	<SubTexture name="idle0005" x="2077" y="336" width="513" height="292" />
	<SubTexture name="idle0006" x="2595" y="336" width="513" height="292" />
	<SubTexture name="idle0007" x="2595" y="336" width="513" height="292" />
	<SubTexture name="idle0008" x="3113" y="336" width="513" height="292" />
	<SubTexture name="idle0009" x="4" y="634" width="513" height="292" />
	<SubTexture name="idle0010" x="522" y="634" width="513" height="292" />
	<SubTexture name="idle0011" x="1040" y="634" width="513" height="292" />
	<SubTexture name="idle0012" x="1559" y="634" width="513" height="292" />
	<SubTexture name="idle0013" x="1559" y="634" width="513" height="292" />
	<SubTexture name="idle0014" x="2077" y="634" width="513" height="292" />
	<SubTexture name="idle0015" x="2595" y="634" width="513" height="292" />
	<SubTexture name="idle0016" x="3113" y="634" width="513" height="292" />
	<SubTexture name="idle0017" x="4" y="931" width="513" height="292" />
	<SubTexture name="idle0018" x="522" y="931" width="513" height="292" />
	<SubTexture name="idle0019" x="522" y="931" width="513" height="292" />
	<SubTexture name="idle0020" x="1040" y="931" width="513" height="292" />
	<SubTexture name="idle0021" x="1559" y="931" width="513" height="292" />
	<SubTexture name="idle0022" x="2077" y="931" width="513" height="292" />
	<SubTexture name="idle0023" x="2595" y="931" width="513" height="292" />
	<SubTexture name="idle0024" x="3113" y="931" width="513" height="292" />
	<SubTexture name="idle0025" x="3113" y="931" width="513" height="292" />
	<SubTexture name="left0000" x="4" y="1228" width="343" height="329" />
	<SubTexture name="left0001" x="352" y="1228" width="343" height="329" />
	<SubTexture name="left0002" x="699" y="1228" width="343" height="329" />
	<SubTexture name="left0003" x="1047" y="1228" width="343" height="329" />
	<SubTexture name="left0004" x="1394" y="1228" width="343" height="329" />
	<SubTexture name="left0005" x="1742" y="1228" width="343" height="329" />
	<SubTexture name="left0006" x="2089" y="1228" width="343" height="329" />
	<SubTexture name="left0007" x="2437" y="1228" width="343" height="329" />
	<SubTexture name="left0008" x="2784" y="1228" width="343" height="329" />
	<SubTexture name="left0009" x="3132" y="1228" width="343" height="329" />
	<SubTexture name="left0010" x="4" y="1563" width="343" height="329" />
	<SubTexture name="right0000" x="352" y="1563" width="521" height="297" />
	<SubTexture name="right0001" x="877" y="1563" width="521" height="297" />
	<SubTexture name="right0002" x="1403" y="1563" width="521" height="297" />
	<SubTexture name="right0003" x="1929" y="1563" width="521" height="297" />
	<SubTexture name="right0004" x="1929" y="1563" width="521" height="297" />
	<SubTexture name="right0005" x="2455" y="1563" width="521" height="297" />
	<SubTexture name="right0006" x="2980" y="1563" width="521" height="297" />
	<SubTexture name="right0007" x="4" y="1897" width="521" height="297" />
	<SubTexture name="right0008" x="530" y="1897" width="521" height="297" />
	<SubTexture name="up0000" x="1056" y="1897" width="407" height="325" />
	<SubTexture name="up0001" x="1467" y="1897" width="407" height="325" />
	<SubTexture name="up0002" x="1879" y="1897" width="407" height="325" />
	<SubTexture name="up0003" x="2290" y="1897" width="407" height="325" />
	<SubTexture name="up0004" x="2702" y="1897" width="407" height="325" />
	<SubTexture name="up0005" x="3113" y="1897" width="407" height="325" />
	<SubTexture name="up0006" x="4" y="2227" width="407" height="325" />
	<SubTexture name="up0007" x="416" y="2227" width="407" height="325" />
	<SubTexture name="up0008" x="827" y="2227" width="407" height="325" />
	<SubTexture name="up0009" x="1239" y="2227" width="407" height="325" />
</TextureAtlas>